catmat
