Metadata-Version: 1.0
Name: catmat-parser
Version: 1.2.1.2
Summary: A simple Catmat (SIASG) XML Service
Home-page: https://github.com/oswluiz/CatmatParser
Author: Oswaldo Ferreira
Author-email: oswluizf@gmail.com
License: UNKNOWN
Download-URL: https://github.com/oswluiz/CatmatParser
Platform: UNKNOWN
